<?xml version="1.0" encoding="UTF-8"?>
<!DOCTYPE hibernate-mapping PUBLIC "-//Hibernate/Hibernate Mapping DTD 3.0//EN" "http://hibernate.sourceforge.net/hibernate-mapping-3.0.dtd">
<!-- Generated Sep 7, 2011 11:37:28 AM by Hibernate Tools 3.2.1.GA -->
<hibernate-mapping>
  <class catalog="m4water" name="org.m4water.server.admin.model.User" table="user">
    <id name="userId" type="string">
      <column length="200" name="user_id"/>
      <generator class="assigned"/>
    </id>
    <property name="firstname" type="string">
      <column length="200" name="firstname" not-null="true"/>
    </property>
    <property name="lastname" type="string">
      <column length="200" name="lastname" not-null="true"/>
    </property>
    <property name="contacts" type="string">
      <column length="200" name="contacts" not-null="true"/>
    </property>
    <property name="password" type="string">
      <column length="200" name="password" not-null="true"/>
    </property>
    <property name="staffProfileId" type="string">
      <column length="200" name="staff_profile_id" not-null="true"/>
    </property>
    <property name="subcountyId" type="string">
      <column length="200" name="subcounty_id" not-null="true"/>
    </property>
    <set inverse="true" name="userAssigneds">
      <key>
        <column length="200" name="user_id" not-null="true"/>
      </key>
      <one-to-many class="org.m4water.server.admin.model.UserAssigned"/>
    </set>
  </class>
</hibernate-mapping>
